opproplot/__init__.py
opproplot/core.py
opproplot/plotting.py
opproplot-0.1.0.dist-info/licenses/LICENSE
opproplot-0.1.0.dist-info/METADATA
opproplot-0.1.0.dist-info/WHEEL
opproplot-0.1.0.dist-info/top_level.txt
opproplot-0.1.0.dist-info/RECORD
