Metadata-Version: 2.4
Name: opproplot
Version: 0.1.0
Summary: Operating profile plots: score histograms + TPR/FPR/accuracy vs threshold for binary classifiers.
Author: Mike Roth
Project-URL: Homepage, https://github.com/<your-username>/opproplot
Requires-Python: >=3.9
License-File: LICENSE
Requires-Dist: numpy
Requires-Dist: matplotlib
Dynamic: license-file
